parimutuelsdk.libs/libkrb5support-d0bcff84.so.0.1
parimutuelsdk.libs/libgssapi_krb5-497db0c6.so.2.2
parimutuelsdk.libs/libselinux-0922c95c.so.1
parimutuelsdk.libs/libssl-cd1d6220.so.1.0.2k
parimutuelsdk.libs/libk5crypto-b1f99d5c.so.3.1
parimutuelsdk.libs/libkeyutils-dfe70bd6.so.1.5
parimutuelsdk.libs/libcom_err-2abe824b.so.2.1
parimutuelsdk.libs/libpcre-9513aab5.so.1.2.0
parimutuelsdk.libs/libkrb5-fcafa220.so.3.3
parimutuelsdk.libs/libcrypto-d3570994.so.1.0.2k
parimutuelsdk-0.1.11.dist-info/METADATA
parimutuelsdk-0.1.11.dist-info/top_level.txt
parimutuelsdk-0.1.11.dist-info/WHEEL
parimutuelsdk-0.1.11.dist-info/RECORD
parimutuelsdk/parimutuelsdk.cpython-311-x86_64-linux-gnu.so
parimutuelsdk/__init__.py
