Metadata-Version: 2.1
Name: parimutuelsdk
Version: 0.1.11
Summary: Python SDK for the HXRO parimutuel options
Author: HXRO
